netdata_llm_agent/__init__.py
netdata_llm_agent/agent.py
netdata_llm_agent/app.py
netdata_llm_agent/cli.py
netdata_llm_agent/tools.py
netdata_llm_agent-0.4.0.dist-info/LICENSE
netdata_llm_agent-0.4.0.dist-info/METADATA
netdata_llm_agent-0.4.0.dist-info/WHEEL
netdata_llm_agent-0.4.0.dist-info/entry_points.txt
netdata_llm_agent-0.4.0.dist-info/top_level.txt
netdata_llm_agent-0.4.0.dist-info/RECORD
