Metadata-Version: 2.2
Name: netdata-llm-agent
Version: 0.4.0
Summary: A language model agent that interacts with Netdata API
Home-page: https://github.com/andrewm4894/netdata-llm-agent
Author: Andrew Maguire
Author-email: andrewm4894@gmail.com
Classifier: Development Status :: 3 - Alpha
Classifier: Intended Audience :: Developers
Classifier: License :: OSI Approved :: MIT License
Classifier: Operating System :: OS Independent
Classifier: Programming Language :: Python :: 3
Classifier: Programming Language :: Python :: 3.8
Classifier: Programming Language :: Python :: 3.9
Classifier: Programming Language :: Python :: 3.10
Requires-Python: >=3.8
License-File: LICENSE
Requires-Dist: aiohappyeyeballs==2.4.4
Requires-Dist: aiohttp==3.11.11
Requires-Dist: aiosignal==1.3.2
Requires-Dist: altair==5.5.0
Requires-Dist: annotated-types==0.7.0
Requires-Dist: anthropic==0.45.2
Requires-Dist: anyio==4.8.0
Requires-Dist: attrs==25.1.0
Requires-Dist: beautifulsoup4==4.12.3
Requires-Dist: blinker==1.9.0
Requires-Dist: cachetools==5.5.1
Requires-Dist: certifi==2025.1.31
Requires-Dist: charset-normalizer==3.4.1
Requires-Dist: click==8.1.8
Requires-Dist: colorama==0.4.6
Requires-Dist: dataclasses-json==0.6.7
Requires-Dist: defusedxml==0.7.1
Requires-Dist: distro==1.9.0
Requires-Dist: frozenlist==1.5.0
Requires-Dist: gitdb==4.0.12
Requires-Dist: gitpython==3.1.44
Requires-Dist: greenlet==3.1.1
Requires-Dist: h11==0.14.0
Requires-Dist: httpcore==1.0.7
Requires-Dist: httpx==0.28.1
Requires-Dist: httpx-sse==0.4.0
Requires-Dist: idna==3.10
Requires-Dist: jinja2==3.1.5
Requires-Dist: jiter==0.8.2
Requires-Dist: jsonpatch==1.33
Requires-Dist: jsonpointer==3.0.0
Requires-Dist: jsonschema==4.23.0
Requires-Dist: jsonschema-specifications==2024.10.1
Requires-Dist: langchain==0.3.17
Requires-Dist: langchain-anthropic==0.3.5
Requires-Dist: langchain-community==0.3.16
Requires-Dist: langchain-core==0.3.33
Requires-Dist: langchain-ollama==0.2.3
Requires-Dist: langchain-openai==0.3.3
Requires-Dist: langchain-text-splitters==0.3.5
Requires-Dist: langgraph==0.2.69
Requires-Dist: langgraph-checkpoint==2.0.10
Requires-Dist: langgraph-sdk==0.1.51
Requires-Dist: langsmith==0.3.3
Requires-Dist: markdown-it-py==3.0.0
Requires-Dist: markdownify==0.14.1
Requires-Dist: markupsafe==3.0.2
Requires-Dist: marshmallow==3.26.0
Requires-Dist: mdurl==0.1.2
Requires-Dist: msgpack==1.1.0
Requires-Dist: multidict==6.1.0
Requires-Dist: mypy-extensions==1.0.0
Requires-Dist: narwhals==1.24.2
Requires-Dist: numpy==1.26.4
Requires-Dist: ollama==0.4.7
Requires-Dist: openai==1.60.2
Requires-Dist: orjson==3.10.15
Requires-Dist: packaging==24.2
Requires-Dist: pandas==2.2.3
Requires-Dist: pillow==11.1.0
Requires-Dist: propcache==0.2.1
Requires-Dist: protobuf==5.29.3
Requires-Dist: pyarrow==19.0.0
Requires-Dist: pydantic==2.10.6
Requires-Dist: pydantic-core==2.27.2
Requires-Dist: pydantic-settings==2.7.1
Requires-Dist: pydeck==0.9.1
Requires-Dist: pygments==2.19.1
Requires-Dist: python-dateutil==2.9.0.post0
Requires-Dist: python-dotenv==1.0.1
Requires-Dist: pytz==2025.1
Requires-Dist: pyyaml==6.0.2
Requires-Dist: referencing==0.36.2
Requires-Dist: regex==2024.11.6
Requires-Dist: requests==2.32.3
Requires-Dist: requests-toolbelt==1.0.0
Requires-Dist: rich==13.9.4
Requires-Dist: rpds-py==0.22.3
Requires-Dist: six==1.17.0
Requires-Dist: smmap==5.0.2
Requires-Dist: sniffio==1.3.1
Requires-Dist: soupsieve==2.6
Requires-Dist: sqlalchemy==2.0.37
Requires-Dist: streamlit==1.41.1
Requires-Dist: tenacity==9.0.0
Requires-Dist: tiktoken==0.8.0
Requires-Dist: toml==0.10.2
Requires-Dist: tornado==6.4.2
Requires-Dist: tqdm==4.67.1
Requires-Dist: typing-extensions==4.12.2
Requires-Dist: typing-inspect==0.9.0
Requires-Dist: tzdata==2025.1
Requires-Dist: urllib3==2.3.0
Requires-Dist: watchdog==6.0.0
Requires-Dist: yarl==1.18.3
Requires-Dist: zstandard==0.23.0
Dynamic: author
Dynamic: author-email
Dynamic: classifier
Dynamic: description
Dynamic: description-content-type
Dynamic: home-page
Dynamic: requires-dist
Dynamic: requires-python
Dynamic: summary
